{
  "currency": {
    "pairs": [
      {
        "i": 222,
        "j": 101,
        "strength": 854.1288
      },
      {
        "i": 222,
        "j": 75,
        "strength": 845.3127
      },
      {
        "i": 222,
        "j": 185,
        "strength": 831.6794
      },
      {
        "i": 222,
        "j": 108,
        "strength": 819.3385
      },
      {
        "i": 222,
        "j": 161,
        "strength": 806.5529
      },
      {
        "i": 222,
        "j": 94,
        "strength": 802.5804
      },
      {
        "i": 222,
        "j": 223,
        "strength": 798.7576
      },
      {
        "i": 222,
        "j": 85,
        "strength": 794.6069
      },
      {
        "i": 222,
        "j": 70,
        "strength": 789.069
      },
      {
        "i": 222,
        "j": 128,
        "strength": 788.5488
      }
    ],
    "color": "#f7c948",
    "label": "Currency Synapse"
  },
  "proper_noun": {
    "pairs": [
      {
        "i": 222,
        "j": 101,
        "strength": 402.55
      },
      {
        "i": 222,
        "j": 185,
        "strength": 400.0339
      },
      {
        "i": 222,
        "j": 75,
        "strength": 395.3339
      },
      {
        "i": 222,
        "j": 161,
        "strength": 394.8793
      },
      {
        "i": 222,
        "j": 108,
        "strength": 385.249
      },
      {
        "i": 222,
        "j": 223,
        "strength": 383.0558
      },
      {
        "i": 222,
        "j": 128,
        "strength": 376.4612
      },
      {
        "i": 222,
        "j": 94,
        "strength": 373.7244
      },
      {
        "i": 222,
        "j": 85,
        "strength": 369.7584
      },
      {
        "i": 222,
        "j": 145,
        "strength": 369.3698
      }
    ],
    "color": "#48f78a",
    "label": "Proper Noun Synapse"
  },
  "punctuation": {
    "pairs": [
      {
        "i": 330,
        "j": 101,
        "strength": 540.7169
      },
      {
        "i": 330,
        "j": 185,
        "strength": 534.4495
      },
      {
        "i": 330,
        "j": 75,
        "strength": 533.7573
      },
      {
        "i": 330,
        "j": 161,
        "strength": 526.3232
      },
      {
        "i": 330,
        "j": 223,
        "strength": 521.1887
      },
      {
        "i": 330,
        "j": 94,
        "strength": 514.5311
      },
      {
        "i": 330,
        "j": 108,
        "strength": 513.1061
      },
      {
        "i": 330,
        "j": 145,
        "strength": 507.3626
      },
      {
        "i": 330,
        "j": 85,
        "strength": 504.4844
      },
      {
        "i": 330,
        "j": 70,
        "strength": 499.4285
      }
    ],
    "color": "#f74848",
    "label": "Punctuation Synapse"
  }
}